MANIFEST.in
README.md
setup.py
XetMap/Func.py
XetMap/__init__.py
XetMap/data/usa.json
xetmap.egg-info/PKG-INFO
xetmap.egg-info/SOURCES.txt
xetmap.egg-info/dependency_links.txt
xetmap.egg-info/requires.txt
xetmap.egg-info/top_level.txt