Metadata-Version: 2.1
Name: xetmap
Version: 1.4
Summary: Libreria que te proporciona direcciones reales de Estados Unidos
Home-page: https://github.com/MrXetwy21/XetMap
Author: MrXetwy21
Author-email: Xetwy21@gmail.com
License: MIT
Platform: UNKNOWN
Classifier: Development Status :: 5 - Production/Stable
Classifier: Environment :: Console
Classifier: Intended Audience :: Developers
Classifier: Programming Language :: Python :: 3
Classifier: Programming Language :: Python :: 3.10
Classifier: License :: OSI Approved :: MIT License
Classifier: Operating System :: OS Independent
Classifier: Topic :: Software Development :: Libraries :: Python Modules
Classifier: Topic :: Software Development :: Testing
Classifier: Topic :: Utilities
Requires-Python: >=3.10
